query_making/query_mk.py
Huggy_qmk-0.0.3.dist-info/METADATA
Huggy_qmk-0.0.3.dist-info/WHEEL
Huggy_qmk-0.0.3.dist-info/top_level.txt
Huggy_qmk-0.0.3.dist-info/RECORD
