Metadata-Version: 2.1
Name: Huggy-qmk
Version: 0.0.3
Summary: oss-dev Huggy query make 0003
Home-page: https://github.com/Huggy2646/qmk0001
Download-URL: https://github.com/Huggy2646/qmk0001/archive/refs/tags/v0.0.1.zip
Author: Seonghyeok Oh
Author-email: 1718772@donga.ac.kr
License: UNKNOWN
Platform: UNKNOWN
Classifier: Programming Language :: Python :: 3
